mfu/__init__.py
mfu/__main__.py
mfu/main.py
mfu/scripts/__init__.py
mfu/scripts/cluster.py
mfu/scripts/config.py
mfu/scripts/doctor.py
mfu/scripts/sync.py
mfu/utils/__init__.py
mfu/utils/forcelink.py
mfu/utils/general.py
mfu-0.0.10.dist-info/METADATA
mfu-0.0.10.dist-info/WHEEL
mfu-0.0.10.dist-info/entry_points.txt
mfu-0.0.10.dist-info/top_level.txt
mfu-0.0.10.dist-info/RECORD
