Metadata-Version: 2.1
Name: mfu
Version: 0.0.10
Summary: Michael's fun utilities
Author-email: Michael Botha <michael@408.co.za>
Requires-Python: >=3.7
Requires-Dist: Click >=8.1.3
Requires-Dist: kubernetes >=25.3.0
Requires-Dist: watchdog >=2.1.9
Requires-Dist: GitPython >=3.1.29
Requires-Dist: requests >=2.28.1
Requires-Dist: python-gitlab >=3.7.0
